VirID/__init__.py
VirID/__main__.py
VirID/assembly_and_basic_annotation.py
VirID/cli.py
VirID/main.py
VirID/phylogenetic_analysis.py
VirID/biolib/__init__.py
VirID/biolib/common.py
VirID/biolib/custom_help_formatter.py
VirID/biolib/exceptions.py
VirID/biolib/logger.py
VirID/config/__init__.py
VirID/config/config.py
VirID/data/ICTV_TAXON.csv
VirID/data/Pathogenicity_VIRUS_CSV.csv
VirID/data/RdRP_ICTV_NR.csv
VirID/data/__init__.py
VirID/data/RdRP_tree_230328/Astro-Poty/Astro-Poty.csv
VirID/data/RdRP_tree_230328/Astro-Poty/Astro-Poty.fas
VirID/data/RdRP_tree_230328/Astro-Poty/Astro-Poty.pdf
VirID/data/RdRP_tree_230328/Astro-Poty/Astro-Poty.phy_phyml_tree.nwk
VirID/data/RdRP_tree_230328/Astro-Poty/Astro-Poty_RAxML_info.txt
VirID/data/RdRP_tree_230328/Astro-Poty/Astro-Poty_RAxML_result.nwk
VirID/data/RdRP_tree_230328/Astro-Poty/Astro-Poty_trimmed_alignment.fas
VirID/data/RdRP_tree_230328/Astro-Poty/Astro-Poty_trimmed_alignment.phy
VirID/data/RdRP_tree_230328/Birna-Permutotetra/Birna-Permutotetra.csv
VirID/data/RdRP_tree_230328/Birna-Permutotetra/Birna-Permutotetra.fas
VirID/data/RdRP_tree_230328/Birna-Permutotetra/Birna-Permutotetra.pdf
VirID/data/RdRP_tree_230328/Birna-Permutotetra/Birna-Permutotetra.phy_phyml_tree.nwk
VirID/data/RdRP_tree_230328/Birna-Permutotetra/Birna-Permutotetra_RAxML_info.txt
VirID/data/RdRP_tree_230328/Birna-Permutotetra/Birna-Permutotetra_RAxML_result.nwk
VirID/data/RdRP_tree_230328/Birna-Permutotetra/Birna-Permutotetra_trimmed_alignment.fas
VirID/data/RdRP_tree_230328/Birna-Permutotetra/Birna-Permutotetra_trimmed_alignment.phy
VirID/data/RdRP_tree_230328/Cysto/Cysto.csv
VirID/data/RdRP_tree_230328/Cysto/Cysto.fas
VirID/data/RdRP_tree_230328/Cysto/Cysto.pdf
VirID/data/RdRP_tree_230328/Cysto/Cysto.phy_phyml_tree.nwk
VirID/data/RdRP_tree_230328/Cysto/Cysto_RAxML_info.txt
VirID/data/RdRP_tree_230328/Cysto/Cysto_RAxML_result.nwk
VirID/data/RdRP_tree_230328/Cysto/Cysto_trimmed_alignment.fas
VirID-2.0.4.dist-info/LICENSE
VirID-2.0.4.dist-info/METADATA
VirID-2.0.4.dist-info/WHEEL
VirID-2.0.4.dist-info/entry_points.txt
VirID-2.0.4.dist-info/top_level.txt
VirID-2.0.4.dist-info/RECORD
