Metadata-Version: 2.1
Name: VirID
Version: 2.0.4
Summary: UNKNOWN
Author: YangZiyue&ShanYongtao
Author-email: yangzy58@mail2.sysu.edu.cn
License: UNKNOWN
Platform: UNKNOWN
License-File: LICENSE
Requires-Dist: Bio
Requires-Dist: biopython
Requires-Dist: DendroPy
Requires-Dist: matplotlib
Requires-Dist: numpy
Requires-Dist: pandas
Requires-Dist: regex
Requires-Dist: seaborn
Requires-Dist: tqdm
